network_mcp/__init__.py
network_mcp/config.py
network_mcp/server.py
network_mcp/models/__init__.py
network_mcp/models/responses.py
network_mcp/tools/__init__.py
network_mcp/tools/capabilities.py
network_mcp/tools/connectivity.py
network_mcp/tools/external_intel.py
network_mcp/tools/local.py
network_mcp/tools/pcap.py
network_mcp/tools/planning.py
network_mcp-0.1.2.dist-info/METADATA
network_mcp-0.1.2.dist-info/WHEEL
network_mcp-0.1.2.dist-info/entry_points.txt
network_mcp-0.1.2.dist-info/licenses/LICENSE
network_mcp-0.1.2.dist-info/RECORD
