Metadata-Version: 2.4
Name: network-mcp
Version: 0.1.2
Summary: Network MCP Server for AI Agents - Connectivity testing and pcap analysis
Project-URL: Homepage, https://github.com/labeveryday/network-mcp
Project-URL: Repository, https://github.com/labeveryday/network-mcp
Project-URL: Issues, https://github.com/labeveryday/network-mcp/issues
Author: Du'An Lightfoot
License: MIT License
License-File: LICENSE
Keywords: dns,mcp,mtr,netops,network,networking,observability,pcap,ping,scapy,traceroute
Classifier: Development Status :: 3 - Alpha
Classifier: Environment :: Console
Classifier: Intended Audience :: Developers
Classifier: Intended Audience :: Information Technology
Classifier: Intended Audience :: System Administrators
Classifier: License :: OSI Approved :: MIT License
Classifier: Programming Language :: Python :: 3
Classifier: Programming Language :: Python :: 3.10
Classifier: Programming Language :: Python :: 3.11
Classifier: Programming Language :: Python :: 3.12
Classifier: Topic :: System :: Networking
Classifier: Topic :: System :: Networking :: Monitoring
Requires-Python: >=3.10
Requires-Dist: dnspython>=2.4.0
Requires-Dist: mcp>=1.0.0
Requires-Dist: pydantic>=2.0.0
Requires-Dist: pyyaml>=6.0.0
Requires-Dist: scapy>=2.5.0
Provides-Extra: dev
Requires-Dist: pytest-asyncio>=0.23.0; extra == 'dev'
Requires-Dist: pytest>=8.0.0; extra == 'dev'
Requires-Dist: ruff>=0.4.0; extra == 'dev'
